scribeauth/__init__.py
scribeauth/__main__.py
scribeauth/scribeauth.py
scribeauth-1.2.0.dist-info/LICENSE.md
scribeauth-1.2.0.dist-info/METADATA
scribeauth-1.2.0.dist-info/WHEEL
scribeauth-1.2.0.dist-info/top_level.txt
scribeauth-1.2.0.dist-info/RECORD
