Metadata-Version: 2.1
Name: scribeauth
Version: 1.2.0
Summary: Library to authenticate to Scribe's platform
Home-page: https://github.com/ScribeLabsAI/ScribeAuth
Author: Ailin Venerus
Author-email: ailin@scribelabs.ai
Classifier: Development Status :: 4 - Beta
Classifier: Intended Audience :: Developers
Classifier: Operating System :: OS Independent
Classifier: License :: OSI Approved :: MIT License
Classifier: Natural Language :: English
Classifier: Programming Language :: Python :: 3.10
Classifier: Topic :: Security
Classifier: Typing :: Typed
Requires-Python: >=3.10.0
License-File: LICENSE.md
Requires-Dist: boto3
Requires-Dist: typing-extensions
